{
  "data_asset_type": null,
  "expectation_suite_name": "my_suite",
  "expectations": [
    {
      "expectation_type": "expect_table_row_count_to_be_between",
      "kwargs": {
        "max_value": 129,
        "min_value": 129
      },
      "meta": {
        "profiler_details": {
          "metric_configuration": {
            "domain_kwargs": {},
            "metric_name": "table.row_count",
            "metric_value_kwargs": null
          },
          "num_batches": 1
        }
      }
    },
    {
      "expectation_type": "expect_table_columns_to_match_set",
      "kwargs": {
        "column_set": [
          "BTC Open",
          "BTC Low",
          "ETH Price",
          "JPM Price",
          "JNJ Price",
          "Sentiment Article 2",
          "XOM Price",
          "Gold Price",
          "Sentiment Article 1",
          "Crude Oil Price",
          "BTC High",
          "BTC Previous Close",
          "BTC Price",
          "MSFT Price",
          "Sentiment Article 3",
          "date"
        ],
        "exact_match": null
      },
      "meta": {
        "profiler_details": {
          "success_ratio": 1.0
        }
      }
    }
  ],
  "ge_cloud_id": null,
  "meta": {
    "citations": [
      {
        "citation_date": "2024-05-25T18:42:08.113394Z",
        "comment": "Created by effective Rule-Based Profiler of OnboardingDataAssistant with the configuration included.\n"
      }
    ],
    "great_expectations_version": "0.18.12"
  }
}